{
  "diagnostics": {
    "checked_at": 1783528870.4766898,
    "summary": "ok"
  },
  "host": "droplet",
  "options": {
    "degraded": false,
    "enabled": true,
    "open_structures": 0,
    "opens_today": {
      "count": 0,
      "daily_cap": 3,
      "date": "2026-07-08",
      "underlyings": []
    },
    "order_submission_enabled": true
  },
  "pushed_at": 1783529146,
  "pushed_at_iso": "2026-07-08T16:45:46Z",
  "reconcile": {
    "last_reconciled_ts": 1783529125.9936078,
    "source": "alpaca_rest",
    "stale": false
  },
  "status": {
    "dryrun": false,
    "errors_last_5min": 0,
    "heartbeat_consecutive_errors": 0,
    "last_heartbeat": 1783529125.9356258,
    "last_heartbeat_age_sec": 19.1871919631958,
    "open_positions": 0,
    "order_submission_enabled": true,
    "regime": "unknown_full",
    "universe_size": 24
  },
  "ws": {
    "bars_seen": 3826,
    "last_bar_ts": 1783529110.997061,
    "unique_symbols": 24
  }
}