{
  "diagnostics": {
    "checked_at": 1783451031.7288854,
    "summary": "ok"
  },
  "host": "droplet",
  "options": {
    "degraded": false,
    "enabled": true,
    "open_structures": 0,
    "opens_today": {
      "count": 0,
      "daily_cap": 3,
      "date": "2026-07-07",
      "underlyings": []
    },
    "order_submission_enabled": true
  },
  "pushed_at": 1783451248,
  "pushed_at_iso": "2026-07-07T19:07:28Z",
  "reconcile": {
    "last_reconciled_ts": 1783451218.6690803,
    "source": "alpaca_rest",
    "stale": false
  },
  "status": {
    "dryrun": false,
    "errors_last_5min": 1,
    "heartbeat_consecutive_errors": 0,
    "last_heartbeat": 1783451218.6640296,
    "last_heartbeat_age_sec": 19.029771089553833,
    "open_positions": 0,
    "order_submission_enabled": true,
    "regime": "unknown_full",
    "universe_size": 24
  },
  "ws": {
    "bars_seen": 6,
    "last_bar_ts": 1783430760.0235095,
    "unique_symbols": 4
  }
}