{
  "diagnostics": {
    "checked_at": 1782935802.0244398,
    "summary": "ok"
  },
  "host": "droplet",
  "options": {
    "degraded": false,
    "enabled": true,
    "open_structures": 0,
    "opens_today": {
      "count": 0,
      "daily_cap": 3,
      "date": "2026-07-01",
      "underlyings": []
    },
    "order_submission_enabled": true
  },
  "pushed_at": 1782936039,
  "pushed_at_iso": "2026-07-01T20:00:39Z",
  "reconcile": {
    "last_reconciled_ts": 1782936037.9097753,
    "source": "alpaca_rest",
    "stale": false
  },
  "status": {
    "dryrun": true,
    "errors_last_5min": 0,
    "heartbeat_consecutive_errors": 421,
    "last_heartbeat": 1782936037.9082298,
    "last_heartbeat_age_sec": 0.25070643424987793,
    "open_positions": 0,
    "order_submission_enabled": true,
    "regime": "unknown",
    "universe_size": 503
  },
  "ws": {
    "bars_seen": 4376,
    "last_bar_ts": 1782936002.093845,
    "unique_symbols": 498
  }
}