{
  "diagnostics": {
    "checked_at": 1782914795.1743872,
    "summary": "ok"
  },
  "host": "droplet",
  "options": {
    "degraded": null,
    "enabled": null,
    "open_structures": 0,
    "opens_today": null,
    "order_submission_enabled": null
  },
  "pushed_at": 1782914883,
  "pushed_at_iso": "2026-07-01T14:08:03Z",
  "reconcile": {
    "last_reconciled_ts": 1782914861.2467947,
    "source": "alpaca_rest",
    "stale": false
  },
  "status": {
    "dryrun": false,
    "errors_last_5min": 0,
    "heartbeat_consecutive_errors": 484,
    "last_heartbeat": 1782914861.2457864,
    "last_heartbeat_age_sec": 14.215330600738525,
    "open_positions": 0,
    "order_submission_enabled": true,
    "regime": "unknown",
    "universe_size": 503
  },
  "ws": {
    "bars_seen": 1204,
    "last_bar_ts": 1782914882.2432125,
    "unique_symbols": 444
  }
}