{
  "diagnostics": {
    "checked_at": 1781684262.6762989,
    "summary": "ok"
  },
  "host": "droplet",
  "options": {
    "degraded": false,
    "enabled": true,
    "open_structures": 0,
    "opens_today": {
      "count": 0,
      "daily_cap": 3,
      "date": "2026-06-17",
      "underlyings": []
    },
    "order_submission_enabled": true,
    "reconcile": {
      "last_reconciled_ts": 1781684292.5478268,
      "stale": false
    }
  },
  "pushed_at": 1781684299,
  "pushed_at_iso": "2026-06-17T08:18:19Z",
  "reconcile": {
    "last_reconciled_ts": 1781684292.8375888,
    "source": "alpaca_rest",
    "stale": null
  },
  "status": {
    "dryrun": true,
    "errors_last_5min": 9,
    "heartbeat_consecutive_errors": 0,
    "heartbeat_write_errors": 0,
    "last_heartbeat": 1781684292.7270539,
    "last_heartbeat_age_sec": 6.8874781131744385,
    "open_positions": 0,
    "order_submission_enabled": false,
    "paused": false,
    "regime": "unknown_full",
    "universe_size": 24
  },
  "ws": {
    "bars_seen": 0
  }
}