{
  "diagnostics": {
    "checked_at": 1783841357.694503,
    "summary": "fmp_fail"
  },
  "host": "droplet",
  "options": {
    "degraded": false,
    "enabled": true,
    "open_structures": 0,
    "opens_today": {
      "count": 0,
      "daily_cap": 3,
      "date": "2026-07-12",
      "underlyings": []
    },
    "order_submission_enabled": true
  },
  "pushed_at": 1783841585,
  "pushed_at_iso": "2026-07-12T07:33:05Z",
  "reconcile": {
    "last_reconciled_ts": 1783841559.0062592,
    "source": "alpaca_rest",
    "stale": false
  },
  "status": {
    "dryrun": false,
    "errors_last_5min": 0,
    "heartbeat_consecutive_errors": 0,
    "last_heartbeat": 1783841559.0043473,
    "last_heartbeat_age_sec": 19.671762466430664,
    "open_positions": 3,
    "order_submission_enabled": true,
    "regime": "full_size",
    "universe_size": 24
  },
  "ws": {
    "bars_seen": 37,
    "last_bar_ts": 1783716600.1555088,
    "unique_symbols": 24
  }
}